csv2postgresql.py
csv2postgresql-0.1.3.dist-info/entry_points.txt
csv2postgresql-0.1.3.dist-info/WHEEL
csv2postgresql-0.1.3.dist-info/METADATA
csv2postgresql-0.1.3.dist-info/LICENSE
csv2postgresql-0.1.3.dist-info/RECORD
