Metadata-Version: 2.1
Name: csv2postgresql
Version: 0.1.3
Summary: Load CSV with header into PostgreSQL
License: GPL-3.0-or-later
Author-email: Francesco Frassinelli <francesco.frassinelli@nina.no>
Requires-Python: >=3.7
Classifier: License :: OSI Approved :: GNU General Public License v3 or later (GPLv3+)
Classifier: Programming Language :: Python :: 3
Classifier: Programming Language :: Python :: 3.10
Classifier: Programming Language :: Python :: 3.7
Classifier: Programming Language :: Python :: 3.8
Classifier: Programming Language :: Python :: 3.9
Requires-Dist: psycopg2-binary~=2.9
Project-URL: homepage, https://github.com/NINAnor/csv2postgresql
Project-URL: repository, https://github.com/NINAnor/csv2postgresql
